Evaluator/__init__.py
Evaluator/data/__init__.py
Evaluator/data/data_reader.py
Evaluator/data/embedding_reader.py
Evaluator/data/validate_files.py
Evaluator/logic/__init__.py
Evaluator/logic/analogy_metrics.py
Evaluator/logic/compare.py
Evaluator/logic/outlier_metrics.py
Evaluator/logic/summary.py
Evaluator/presentation/__init__.py
Evaluator/presentation/evaluate_metrics.py
embedding_evaluator/__init__.py
embedding_evaluator/data/__init__.py
embedding_evaluator/data/data_reader.py
embedding_evaluator/data/embedding_reader.py
embedding_evaluator/data/load_models.py
embedding_evaluator/data/validate_files.py
embedding_evaluator/data/validate_input.py
embedding_evaluator/logic/__init__.py
embedding_evaluator/logic/analogy_metrics.py
embedding_evaluator/logic/calculate_metrics.py
embedding_evaluator/logic/compare.py
embedding_evaluator/logic/iterator.py
embedding_evaluator/logic/outlier_metrics.py
embedding_evaluator/logic/summary.py
embedding_evaluator/logic/validate_embedding.py
embedding_evaluator/logic/vocab.py
embedding_evaluator/presentation/__init__.py
embedding_evaluator/presentation/evaluate_metrics.py
src/__init__.py
src/data/__init__.py
src/data/data_reader.py
src/data/embedding_reader.py
src/data/validate_files.py
src/embedding_evaluator/__init__.py
src/embedding_evaluator/data/__init__.py
src/embedding_evaluator/data/data_reader.py
src/embedding_evaluator/data/embedding_reader.py
src/embedding_evaluator/data/validate_files.py
src/embedding_evaluator/logic/__init__.py
src/embedding_evaluator/logic/analogy_metrics.py
src/embedding_evaluator/logic/compare.py
src/embedding_evaluator/logic/outlier_metrics.py
src/embedding_evaluator/logic/summary.py
src/embedding_evaluator/presentation/__init__.py
src/embedding_evaluator/presentation/evaluate_metrics.py
src/logic/__init__.py
src/logic/analogy_metrics.py
src/logic/compare.py
src/logic/outlier_metrics.py
src/logic/summary.py
src/presentation/__init__.py
src/presentation/evaluate_metrics.py
embedding_evaluator-0.0.1.dist-info/METADATA
embedding_evaluator-0.0.1.dist-info/WHEEL
embedding_evaluator-0.0.1.dist-info/top_level.txt
embedding_evaluator-0.0.1.dist-info/RECORD
