Metadata-Version: 2.1
Name: embedding-evaluator
Version: 0.0.1
Summary: Embedding Evaluator
Home-page: UNKNOWN
Author: Data & Analytics Research
Author-email: analytics.dar@take.net
Maintainer: daresearch
Maintainer-email: anaytics.dar@take.net
License: MIT License
Keywords: embedding,evaluation
Platform: UNKNOWN
Classifier: Programming Language :: Python :: 3
Classifier: Operating System :: OS Independent
Requires-Dist: gensim (==3.8.3)
Requires-Dist: scikit-learn (==0.23.2)
Requires-Dist: numpy (==1.21.0)
Requires-Dist: pandas (==1.3.0)
